tinynn/__init__.py
tinynn/activations/__init__.py
tinynn/activations/relu.py
tinynn/activations/sigmoid.py
tinynn/activations/softmax.py
tinynn/layers/__init__.py
tinynn/layers/dense.py
tinynn/loss_functions/__init__.py
tinynn/loss_functions/categorical_cross_entrpy.py
tinynn/loss_functions/loss.py
tinynn/loss_functions/mean_square_error.py
tinynn/models/__init__.py
tinynn/models/sequential.py
tinynn/optimizers/__init__.py
tinynn/optimizers/adagrad.py
tinynn/optimizers/adam.py
tinynn/optimizers/rmsprop.py
tinynn/optimizers/sgd.py
tinynn_py-1.0.2.dist-info/LICENSE
tinynn_py-1.0.2.dist-info/METADATA
tinynn_py-1.0.2.dist-info/WHEEL
tinynn_py-1.0.2.dist-info/top_level.txt
tinynn_py-1.0.2.dist-info/RECORD
