Metadata-Version: 2.1
Name: tinynn-py
Version: 1.0.2
Summary: A tiny neural network library.
Author: Praneeth Vasarla
License-File: LICENSE
Requires-Dist: numpy
